[
  {
    "consultant_id": "4d5e6f7g-8h9i-0j1k-2l3m-4n5o6p7q8r9s",
    "name": "Dr. Emily Green",
    "position": "Senior Environmental Consultant",
    "expertise": ["Environmental Impact Assessment", "Emissions Reduction Planning"],
    "profilePicture": "https://avatar.iran.liara.run/public/77",
    "email": "emily.green@envirotech.com",
    "rating": 4.9
  },
  {
    "consultant_id": "5e6f7g8h-9i0j-1k2l-3m4n-5o6p7q8r9s0t",
    "name": "Engr. Michael Brown",
    "position": "Wastewater Treatment Engineer",
    "expertise": ["Wastewater Engineering", "Sustainable Water Use"],
    "profilePicture": "https://avatar.iran.liara.run/public/38",
    "email": "michael.brown@envirotech.com",
    "rating": 4.8
  },
  {
    "consultant_id": "6f7g8h9i-0j1k-2l3m-4n5o-6p7q8r9s0t1u",
    "name": "Dr. Sarah White",
    "position": "Renewable Energy Specialist",
    "expertise": ["Renewable Energy", "Environmental Impact Assessment"],
    "profilePicture": "https://avatar.iran.liara.run/public/90",
    "email": "sarah.white@envirotech.com",
    "rating": 4.7
  },
  {
    "consultant_id": "7g8h9i0j-1k2l-3m4n-5o6p-7q8r9s0t1u2v",
    "name": "Dr. David Lee",
    "position": "Water Resources Expert",
    "expertise": ["Water Quality Management", "Sustainable Water Use"],
    "profilePicture": "https://avatar.iran.liara.run/public/16",
    "email": "david.lee@envirotech.com",
    "rating": 4.6
  },
  {
    "consultant_id": "8h9i0j1k-2l3m-4n5o-6p7q-8r9s0t1u2v3w",
    "name": "Dr. Lisa Chen",
    "position": "Air Quality Specialist",
    "expertise": ["Air Quality", "Environmental Impact Assessment"],
    "profilePicture": "https://avatar.iran.liara.run/public/98",
    "email": "lisa.chen@envirotech.com",
    "rating": 4.8
  },
  {
    "consultant_id": "9i0j1k2l-3m4n-5o6p-7q8r-9s0t1u2v3w4x",
    "name": "Prof. Robert Taylor",
    "position": "Waste Management Expert",
    "expertise": ["Environmental Data Analysis", "Ecosystem Restoration"],
    "profilePicture": "https://avatar.iran.liara.run/public/15",
    "email": "robert.taylor@envirotech.com",
    "rating": 4.7
  },
  {
    "consultant_id": "0j1k2l3m-4n5o-6p7q-8r9s-0t1u2v3w4x5y",
    "name": "Dr. Amanda Johnson",
    "position": "Environmental Policy Advisor",
    "expertise": ["Compliance and Regulatory Support", "Environmental Impact Assessment"],
    "profilePicture": "https://avatar.iran.liara.run/public/79",
    "email": "amanda.johnson@envirotech.com",
    "rating": 4.9
  }
]